LICENSE
MANIFEST.in
README.md
package.json
setup.py
thinks_dash_touchable_component/__init__.py
thinks_dash_touchable_component/_imports_.py
thinks_dash_touchable_component.egg-info/PKG-INFO
thinks_dash_touchable_component.egg-info/SOURCES.txt
thinks_dash_touchable_component.egg-info/dependency_links.txt
thinks_dash_touchable_component.egg-info/top_level.txt