Metadata-Version: 2.1
Name: thinks-dash-touchable-component
Version: 1.0.0
Summary: Dash Toucheable Component
Author: thinkup-sol <s_matsumoto@thinkup-sol.co.jp>
License: MIT
Classifier: Framework :: Dash
License-File: LICENSE
